pyquantify/__init__.py
pyquantify/bert_summarizer.py
pyquantify/core.py
pyquantify/main.py
pyquantify/sentiment_analyzer.py
pyquantify/utils/__init__.py
pyquantify/utils/export_manager.py
pyquantify/utils/input_handler.py
pyquantify/utils/misc.py
pyquantify-1.2.0.dist-info/LICENSE
pyquantify-1.2.0.dist-info/METADATA
pyquantify-1.2.0.dist-info/WHEEL
pyquantify-1.2.0.dist-info/entry_points.txt
pyquantify-1.2.0.dist-info/top_level.txt
pyquantify-1.2.0.dist-info/RECORD
